datastructures/singlylinkedlist.py
dsal-1.0.0.dist-info/LICENSE
dsal-1.0.0.dist-info/METADATA
dsal-1.0.0.dist-info/WHEEL
dsal-1.0.0.dist-info/top_level.txt
dsal-1.0.0.dist-info/RECORD
