Metadata-Version: 2.1
Name: dsal
Version: 1.0.0
Summary: A Python package to implement datastructures .
Home-page: https://github.com/chelladuraimohanraj/datastructures
Author: mohanraj
Author-email: chelladuraimohanraj@gmail.com
License: MIT
Platform: UNKNOWN
Classifier: License :: OSI Approved :: MIT License
Classifier: Programming Language :: Python :: 3
Classifier: Programming Language :: Python :: 3.7
